{
  "db_name": "MySQL",
  "query": "\n            SELECT registered_user_id IS NOT NULL AS \"is_binded: bool\"\n            FROM authed_tokens\n            WHERE id = ?\n            ",
  "describe": {
    "columns": [
      {
        "ordinal": 0,
        "name": "is_binded: bool",
        "type_info": {
          "type": "LongLong",
          "flags": "NOT_NULL | BINARY",
          "max_size": 1
        }
      }
    ],
    "parameters": {
      "Right": 1
    },
    "nullable": [
      false
    ]
  },
  "hash": "87bd64f6c80b24fa26d784fa57fa7143a355c5fef2477f61989dfc5b1599c3bf"
}
